fred_forecaster/__init__.py
fred_forecaster/calibration.py
fred_forecaster/constants.py
fred_forecaster/data.py
fred_forecaster/visualization.py
fred_forecaster/models/__init__.py
fred_forecaster/models/bayesian.py
fred_forecaster/models/sarimax.py
tests/__init__.py
tests/conftest.py
tests/test_bayesian.py
tests/test_calibration.py
tests/test_data.py
tests/test_forecast.py
tests/test_visualization.py
fred_forecaster-0.1.0.dist-info/LICENSE
fred_forecaster-0.1.0.dist-info/METADATA
fred_forecaster-0.1.0.dist-info/WHEEL
fred_forecaster-0.1.0.dist-info/top_level.txt
fred_forecaster-0.1.0.dist-info/RECORD
