Metadata-Version: 2.2
Name: fred_forecaster
Version: 0.1.0
Summary: Time series forecasting for FRED economic data
Home-page: https://github.com/maxghenis/fred-forecaster
Author-email: Max Ghenis <max@example.com>
License: MIT
Project-URL: Homepage, https://github.com/maxghenis/fred-forecaster
Project-URL: Bug Tracker, https://github.com/maxghenis/fred-forecaster/issues
Classifier: Programming Language :: Python :: 3
Classifier: License :: OSI Approved :: MIT License
Classifier: Operating System :: OS Independent
Requires-Python: >=3.8
License-File: LICENSE
Requires-Dist: numpy>=1.25.0
Requires-Dist: pandas>=2.0.0
Requires-Dist: fredapi>=0.5.0
Requires-Dist: scipy<1.12.0,>=1.9.0
Requires-Dist: statsmodels>=0.14.0
Requires-Dist: matplotlib>=3.7.0
Requires-Dist: plotly>=5.14.0
Requires-Dist: pymc>=5.0.0
Requires-Dist: arviz>=0.16.0
Requires-Dist: aesara>=2.9.0
Provides-Extra: dev
Requires-Dist: pytest; extra == "dev"
Requires-Dist: pytest-cov; extra == "dev"
Requires-Dist: black; extra == "dev"
Requires-Dist: isort; extra == "dev"
Requires-Dist: flake8; extra == "dev"
Requires-Dist: mypy; extra == "dev"
Provides-Extra: app
Requires-Dist: streamlit; extra == "app"
